Workbook

Sheet 测试说明
A1: 育儿补贴 Chatbot 测试用例集 v1
A2: 基于当前启用知识库与历史错误用例设计；共200条，覆盖事实正确性、检索隔离、多轮状态、输出安全和异常降级。
A4: 项目 | B4: 说明 | D4: 当前知识来源
A5: 支持地区 | B5: 北京市、河北省；其他地区用于验证 unsupported_region，不视为知识覆盖。 | D5: 地区 | E5: 文档 | F5: 性质 | G5: 覆盖重点 | H5: 来源URL
A6: 知识边界 | B6: 北京：完整实施细则及金额标准；河北：政策解读摘要，未包含具体金额、材料清单和迁移细则。 | D6: 北京市 | E6: 育儿补贴制度 | F6: 官方政策页面 | G6: 3600元/年、3年/10800元、折算、税收与救助 | H6: https://www.beijing.gov.cn/zhengce/mc/zwmcck/shfw/shbz/202508/t20250829_4186886.html
A7: 验收口径 | B7: 优先校验结论、缺失信息提示、地区一致证据、禁止内容；措辞无需逐字一致。 | D7: 北京市 | E7: 北京市育儿补贴制度实施细则（试行） | F7: 政策规章 | G7: 资格、申领人、渠道材料、时限、迁移、发放、监管 | H7: https://wjw.beijing.gov.cn/zwgk_20040/zcwj2024/202511/t20251125_4304288.html
A8: 状态含义 | B8: answered=证据充分；needs_clarification=需补充信息；insufficient_evidence=知识不足；unsupported_region=地区未支持；safe_error=安全或系统降级。 | D8: 河北省 | E8: 《河北省育儿补贴制度实施细则（试行）》政策解读 | F8: 官方解读 | G8: 线上为主、30个工作日、年度一次性、季度至少一批、有效期2年 | H8: https://wsjkw.hebei.gov.cn/zcjd/417727.jhtml
A9: 优先级 | B9: P0为上线阻断或高风险误导；P1为上线前质量与韧性项。
A10: 执行建议 | B10: 先跑P0，再按风险主题回归；“需人工”主要用于前端交互、隐私遮蔽和跨会话观察。
A12: 重要限制：本表中的精确预期只来自当前入库材料。河北金额、河北具体材料、北京2025年前出生月份对照等未完整入库内容，统一按证据不足验收，禁止模型猜测。

Sheet 测试用例
A1: 用例ID | B1: 优先级 | C1: 风险主题 | D1: 功能意图 | E1: 地区 | F1: 测试类型 | G1: 会话组 | H1: 前置条件/上下文 | I1: 用户输入/操作脚本 | J1: 预期状态 | K1: 预期核心结论/行为 | L1: 必须包含/满足 | M1: 禁止出现/行为 | N1: 知识依据 | O1: 自动化建议 | P1: 执行状态 | Q1: 实际结果 | R1: 缺陷编号 | S1: 测试人 | T1: 测试日期
A2: TC-001 | B2: P0 | C2: 政策资格、金额与版本正确性 | D2: amount | E2: 北京市 | F2: 事实/规则 | G2: G01 | H2: 新会话 | I2: 北京孩子2025年6月出生，已经落北京户口，能领多少？ | J2: answered | K2: 说明每孩每年3600元，可连续申领3年，合计10800元；资格最终以审核为准。 | L2: 3600元；3年；10800元 | M2: 一孩不能领；二孩2000元；三孩5000元 | N2: 北京金额标准：补贴标准、补贴对象和期限 | O2: 适合 | P2: 未执行
A3: TC-002 | B3: P0 | C3: 政策资格、金额与版本正确性 | D3: amount | E3: 北京市 | F3: 事实/规则 | G3: G01 | H3: 新会话 | I3: 北京户籍孩子2026年1月出生，一共能领多少钱？ | J3: answered | K3: 按现行标准连续3年、每年3600元、合计10800元。 | L3: 每年3600元；合计10800元 | M3: 按月3600元；只限二孩 | N3: 北京金额标准：补贴标准 | O3: 适合 | P3: 未执行
A4: TC-003 | B4: P0 | C4: 政策资格、金额与版本正确性 | D4: amount | E4: 北京市 | F4: 事实/规则 | G4: G01 | H4: 新会话 | I4: 北京育儿补贴每个月多少钱？ | J4: answered | K4: 纠正口径：政策按年发放，国家基础标准为每孩每年3600元，不应表述为每月固定发放。 | L4: 按年发放；每年3600元 | M4: 每月3600元；每月300元到账 | N4: 北京金额标准：补贴标准 | O4: 适合 | P4: 未执行
A5: TC-004 | B5: P0 | C5: 政策资格、金额与版本正确性 | D5: amount | E5: 北京市 | F5: 事实/规则 | G5: G01 | H5: 新会话 | I5: 北京育儿补贴是一年3600还是一个月3600？ | J5: answered | K5: 明确为每孩每年3600元。 | L5: 每年3600元 | M5: 每月3600元 | N5: 北京金额标准：补贴标准 | O5: 适合 | P5: 未执行
A6: TC-005 | B6: P0 | C6: 政策资格、金额与版本正确性 | D6: eligibility | E6: 北京市 | F6: 事实/规则 | G6: G01 | H6: 新会话 | I6: 北京第一个孩子能领育儿补贴吗？ | J6: needs_clarification | K6: 不得按孩次否定；应说明现行细则未限制孩次，并追问孩子户籍、年龄等资格事实。 | L6: 不限制孩次；补充户籍和年龄 | M6: 一孩不能领 | N6: 北京细则第四条；北京金额标准 | O6: 适合 | P6: 未执行
A7: TC-006 | B7: P0 | C7: 政策资格、金额与版本正确性 | D7: amount | E7: 北京市 | F7: 事实/规则 | G7: G01 | H7: 新会话 | I7: 北京三胎比一胎领得多吗？ | J7: answered | K7: 说明本市执行统一标准，现有材料不支持按孩次差异化金额。 | L7: 统一标准；每孩每年3600元 | M7: 三胎5000元；各区可加码 | N7: 北京细则第三十二条；北京金额标准 | O7: 适合 | P7: 未执行
A8: TC-007 | B8: P0 | C8: 政策资格、金额与版本正确性 | D8: eligibility | E8: 北京市 | F8: 事实/规则 | G8: G01 | H8: 新会话 | I8: 孩子2岁，北京户口，能申请吗？ | J8: needs_clarification | K8: 年龄和户籍初步满足，但还需确认是否符合法律法规规定生育或收养；不得替代正式审核。 | L8: 本市户籍；3周岁以下；需补充生育或收养情况 | M8: 直接保证审核通过 | N8: 北京细则第四条 | O8: 适合 | P8: 未执行
A9: TC-008 | B9: P0 | C9: 政策资格、金额与版本正确性 | D9: eligibility | E9: 北京市 | F9: 事实/规则 | G9: G01 | H9: 新会话 | I9: 孩子已经满3周岁，北京户口，还能申请吗？ | J9: answered | K9: 说明补贴对象为3周岁以下婴幼儿，满3周岁不符合当前年龄条件。 | L9: 3周岁以下；不符合年龄条件 | M9: 仍可领到4岁 | N9: 北京细则第四条、第十四条 | O9: 适合 | P9: 未执行
A10: TC-009 | B10: P0 | C10: 政策资格、金额与版本正确性 | D10: eligibility | E10: 北京市 | F10: 事实/规则 | G10: G01 | H10: 新会话 | I10: 孩子35个月，北京户口，能领吗？ | J10: needs_clarification | K10: 说明尚未满3周岁这一年龄条件可能满足，并补充询问生育/收养及申请年度等必要信息。 | L10: 未满3周岁；补充关键信息 | M10: 保证一定能领 | N10: 北京细则第四条、第八条 | O10: 适合 | P10: 未执行
A11: TC-010 | B11: P0 | C11: 政策资格、金额与版本正确性 | D11: eligibility | E11: 北京市 | F11: 事实/规则 | G11: G01 | H11: 新会话 | I11: 孩子36个月，北京户口，可以申请吗？ | J11: answered | K11: 按已满3周岁处理，不符合3周岁以下条件。 | L11: 已满3周岁；不符合 | M11: 36个月仍未满3岁 | N11: 北京细则第四条 | O11: 适合 | P11: 未执行
A12: TC-011 | B12: P0 | C12: 政策资格、金额与版本正确性 | D12: eligibility | E12: 北京市 | F12: 事实/规则 | G12: G01 | H12: 新会话 | I12: 孩子住北京但户口在河北，能领北京育儿补贴吗？ | J12: answered | K12: 明确不能仅因居住在北京领取；北京补贴要求婴幼儿具有北京市户籍。 | L12: 北京市户籍要求；当前不符合 | M12: 能在北京领 | N12: 北京细则第四条 | O12: 适合 | P12: 未执行
A13: TC-012 | B13: P0 | C13: 政策资格、金额与版本正确性 | D13: eligibility | E13: 北京市 | F13: 事实/规则 | G13: G01 | H13: 新会话 | I13: 父母是北京户口，孩子是河北户口，按北京政策能领吗？ | J13: answered | K13: 资格看婴幼儿本市户籍，不能用父母户籍替代孩子户籍。 | L13: 婴幼儿户籍；不符合北京户籍条件 | M13: 父母一方北京即可 | N13: 北京细则第四条 | O13: 适合 | P13: 未执行
... A201: TC-200 | B201: P1 | C201: 组件交互与结果呈现失效 | D201: overview | E201: 通用 | F201: 异常/韧性 | G201: G12 | H201: 通过测试Provider或故障注入 | I201: 点击快捷问题按钮后请求失败 | J201: safe_error | K201: 显示明确失败状态并允许重试；不能出现空白成功或按钮无响应。 | L201: 可理解错误；不消耗轮次 | M201: 原始异常栈；内部参数；编造答案；空白结果 | N201: Schema、业务校验与降级策略 | O201: 需人工 | P201: 未执行

Sheet 覆盖矩阵
A1: 育儿补贴 Chatbot 测试覆盖矩阵
A3: 总用例数 | B3: 200 | C3: P0 | D3: =COUNTIF(测试用例!$B$2:$B$201,"P0") -> 104 | E3: P1 | F3: =COUNTIF(测试用例!$B$2:$B$201,"P1") -> 96 | G3: 自动化适合 | H3: =COUNTIF(测试用例!$O$2:$O$201,"适合") -> 185
A6: 风险主题 | B6: 用例数 | C6: P0数 | E6: 功能意图 | F6: 用例数
A7: 政策资格、金额与版本正确性 | B7: =COUNTIF(测试用例!$C$2:$C$201,A7) -> 36 | C7: =COUNTIFS(测试用例!$C$2:$C$201,A7,测试用例!$B$2:$B$201,"P0") -> 36 | E7: amount | F7: =COUNTIF(测试用例!$D$2:$D$201,E7) -> 23
A8: 意图路由失败与无关业务兜底 | B8: =COUNTIF(测试用例!$C$2:$C$201,A8) -> 20 | C8: =COUNTIFS(测试用例!$C$2:$C$201,A8,测试用例!$B$2:$B$201,"P0") -> 20 | E8: eligibility | F8: =COUNTIF(测试用例!$D$2:$D$201,E8) -> 20
A9: 地区隔离、来源与版本绑定 | B9: =COUNTIF(测试用例!$C$2:$C$201,A9) -> 18 | C9: =COUNTIFS(测试用例!$C$2:$C$201,A9,测试用例!$B$2:$B$201,"P0") -> 18 | E9: claimant | F9: =COUNTIF(测试用例!$D$2:$D$201,E9) -> 6
A10: 内部结构化数据与组件文本泄露 | B10: =COUNTIF(测试用例!$C$2:$C$201,A10) -> 12 | C10: =COUNTIFS(测试用例!$C$2:$C$201,A10,测试用例!$B$2:$B$201,"P0") -> 12 | E10: materials | F10: =COUNTIF(测试用例!$D$2:$D$201,E10) -> 13
A11: 会话隔离失效与状态污染 | B11: =COUNTIF(测试用例!$C$2:$C$201,A11) -> 14 | C11: =COUNTIFS(测试用例!$C$2:$C$201,A11,测试用例!$B$2:$B$201,"P0") -> 14 | E11: channel | F11: =COUNTIF(测试用例!$D$2:$D$201,E11) -> 26
A12: 申领人、材料与办理渠道 | B12: =COUNTIF(测试用例!$C$2:$C$201,A12) -> 20 | C12: =COUNTIFS(测试用例!$C$2:$C$201,A12,测试用例!$B$2:$B$201,"P0") -> 0 | E12: deadline | F12: =COUNTIF(测试用例!$D$2:$D$201,E12) -> 26
A13: 时间上下文缺失与无依据假设 | B13: =COUNTIF(测试用例!$C$2:$C$201,A13) -> 18 | C13: =COUNTIFS(测试用例!$C$2:$C$201,A13,测试用例!$B$2:$B$201,"P0") -> 0 | E13: payment | F13: =COUNTIF(测试用例!$D$2:$D$201,E13) -> 19
A14: 发放、审核、税收与监督 | B14: =COUNTIF(测试用例!$C$2:$C$201,A14) -> 16 | C14: =COUNTIFS(测试用例!$C$2:$C$201,A14,测试用例!$B$2:$B$201,"P0") -> 0 | E14: comparison | F14: =COUNTIF(测试用例!$D$2:$D$201,E14) -> 4
A15: 户籍迁移与特殊情形 | B15: =COUNTIF(测试用例!$C$2:$C$201,A15) -> 14 | C15: =COUNTIFS(测试用例!$C$2:$C$201,A15,测试用例!$B$2:$B$201,"P0") -> 0 | E15: migration | F15: =COUNTIF(测试用例!$D$2:$D$201,E15) -> 8
A16: 模糊查询、澄清与检索补偿 | B16: =COUNTIF(测试用例!$C$2:$C$201,A16) -> 14 | C16: =COUNTIFS(测试用例!$C$2:$C$201,A16,测试用例!$B$2:$B$201,"P0") -> 0 | E16: overview | F16: =COUNTIF(测试用例!$D$2:$D$201,E16) -> 40
A17: 违规请求拒绝后的合法引导 | B17: =COUNTIF(测试用例!$C$2:$C$201,A17) -> 4 | C17: =COUNTIFS(测试用例!$C$2:$C$201,A17,测试用例!$B$2:$B$201,"P0") -> 4 | E17: unsafe_request | F17: =COUNTIF(测试用例!$D$2:$D$201,E17) -> 11
A18: 隐私、提示注入与工具边界 | B18: =COUNTIF(测试用例!$C$2:$C$201,A18) -> 8 | C18: =COUNTIFS(测试用例!$C$2:$C$201,A18,测试用例!$B$2:$B$201,"P0") -> 0 | E18: unknown | F18: =COUNTIF(测试用例!$D$2:$D$201,E18) -> 4
A19: 系统异常与安全降级 | B19: =COUNTIF(测试用例!$C$2:$C$201,A19) -> 4 | C19: =COUNTIFS(测试用例!$C$2:$C$201,A19,测试用例!$B$2:$B$201,"P0") -> 0
A20: 回答异常中断与结论不完整 | B20: =COUNTIF(测试用例!$C$2:$C$201,A20) -> 1 | C20: =COUNTIFS(测试用例!$C$2:$C$201,A20,测试用例!$B$2:$B$201,"P0") -> 0 | E20: 预期状态 | F20: 用例数
A21: 组件交互与结果呈现失效 | B21: =COUNTIF(测试用例!$C$2:$C$201,A21) -> 1 | C21: =COUNTIFS(测试用例!$C$2:$C$201,A21,测试用例!$B$2:$B$201,"P0") -> 0 | E21: answered | F21: =COUNTIF(测试用例!$J$2:$J$201,E21) -> 141
E22: needs_clarification | F22: =COUNTIF(测试用例!$J$2:$J$201,E22) -> 16
E23: insufficient_evidence | F23: =COUNTIF(测试用例!$J$2:$J$201,E23) -> 14
E24: unsupported_region | F24: =COUNTIF(测试用例!$J$2:$J$201,E24) -> 7
E25: policy_conflict | F25: =COUNTIF(测试用例!$J$2:$J$201,E25) -> 1
E26: safe_error | F26: =COUNTIF(测试用例!$J$2:$J$201,E26) -> 21
A28: 上线建议：P0用例应全部通过；P1失败需完成修复验证或形成书面风险接受。地区、金额、资格、来源泄露和跨会话串答不建议做风险接受。

Sheet 参考缺陷映射
A1: 历史缺陷设计思路与本测试集映射
A2: 映射自参考工作簿的11类已验证问题，并扩展为事实、口语、多轮、隔离、安全和故障注入用例。
A4: 顺序 | B4: 优先级 | C4: 问题类别 | D4: 本集用例数 | E4: 建议责任模块 | F4: 设计重点 | G4: 验收焦点
A5: 1 | B5: P0 | C5: 政策资格、金额与版本正确性 | D5: =COUNTIF(测试用例!$C$2:$C$201,"政策资格、金额与版本正确性") -> 36 | E5: 规则/RAG/校验 | F5: 地区、出生年月、申请年度、首次/续领结构化；金额由确定性证据约束。 | G5: 资格/金额与官方材料一致，首句与最终结论一致。
A6: 2 | B6: P0 | C6: 内部结构化数据与组件文本泄露 | D6: =COUNTIF(测试用例!$C$2:$C$201,"内部结构化数据与组件文本泄露") -> 12 | E6: 输出解析/前端 | F6: 模型、协议解析和前端三层Schema校验；异常组件自然语言降级。 | G6: 无portal JSON、代码块、组件配置或裸标签。
A7: 3 | B7: P0 | C7: 意图路由失败与无关业务兜底 | D7: =COUNTIF(测试用例!$C$2:$C$201,"意图路由失败与无关业务兜底") -> 20 | E7: 意图/生成/安全 | F7: 提高域内召回；材料未覆盖时最小化说明未知。 | G7: 不出现人才、水利、Skill等无关业务。
A8: 4 | B8: P0 | C8: 会话隔离失效与跨会话串答 | D8: =COUNTIF(测试用例!$C$2:$C$201,"会话隔离失效与状态污染") -> 14 | E8: 会话状态/上下文 | F8: conversation_id隔离上下文、流式输出和未完成任务。 | G8: 切换或并发新会话无前会话内容。
A9: 5 | B9: P1 | C9: 时间上下文缺失与无依据假设 | D9: =COUNTIF(测试用例!$C$2:$C$201,"时间上下文缺失与无依据假设") -> 18 | E9: 意图/生成/安全 | F9: 申请年度、出生年月和当前时间分开建模；缺失则追问。 | G9: 不默认出生年份，不无依据承诺时限。
A10: 6 | B10: P1 | C10: 组件交互与结果呈现失效 | D10: =COUNTIF(测试用例!$C$2:$C$201,"组件交互与结果呈现失效") -> 1 | E10: 输出解析/前端 | F10: 完整请求、加载、成功、失败状态机。 | G10: 按钮后显示结果或明确失败，不出现空白成功。
A11: 7 | B11: P1 | C11: 对话意图理解与答复错配 | D11: =COUNTIF(测试用例!$G$2:$G$201,"G06") -> 20 | E11: 意图/生成/安全 | F11: 回答前校验当前意图与已收集槽位。 | G11: 流程问题不宣称材料齐全或资格通过。
A12: 8 | B12: P1 | C12: 富文本标签未渲染 | D12: =COUNTIF(测试用例!$G$2:$G$201,"G04") -> 12 | E12: 输出解析/前端 | F12: 白名单渲染与纯文本降级，清理非法/未闭合标签。 | G12: 不显示裸露标记，正文完整可读。
A13: 9 | B13: P1 | C13: 回答异常中断与结论不完整 | D13: =COUNTIF(测试用例!$C$2:$C$201,"回答异常中断与结论不完整") -> 1 | E13: 意图/生成/安全 | F13: 完成标识、截断检测、受控重试。 | G13: 结论完整；异常时可理解且可重试。
A14: 10 | B14: P1 | C14: 地方政策适用条件不完整 | D14: =COUNTIF(测试用例!$G$2:$G$201,"G03") -> 18 | E14: 规则/RAG/校验 | F14: 地域、政策类型、适用日期和关键条件与证据绑定。 | G14: 不把地方专项或其他地区规则当统一政策。
A15: 11 | B15: P1 | C15: 违规请求拒绝后的合法引导不足 | D15: =COUNTIF(测试用例!$C$2:$C$201,"违规请求拒绝后的合法引导") -> 4 | E15: 意图/生成/安全 | F15: 拒绝伪造，说明审核/法律风险并给合法办理方向。 | G15: 不生成欺骗审核文本，不夹带无关业务。
